filib/__init__.py
filib/_version.py
filib/helpers.py
filib/oanda.py
filib/utils.py
filib-0.6.0.dist-info/LICENSE
filib-0.6.0.dist-info/METADATA
filib-0.6.0.dist-info/WHEEL
filib-0.6.0.dist-info/top_level.txt
filib-0.6.0.dist-info/RECORD
