Metadata-Version: 2.1
Name: filib
Version: 0.6.0
Summary: Factor Investing Library
Home-page: https://github.com/prmkowalski/filib
Author: Paweł Kowalski
Author-email: prm.kowalski@gmail.com
License: Apache License 2.0
Project-URL: Bug Tracker, https://github.com/prmkowalski/filib/issues
Project-URL: Source Code, https://github.com/prmkowalski/filib
Classifier: Development Status :: 3 - Alpha
Classifier: Intended Audience :: Developers
Classifier: License :: OSI Approved :: Apache Software License
Classifier: Operating System :: OS Independent
Classifier: Programming Language :: Python :: 3.6
Classifier: Programming Language :: Python :: 3.7
Classifier: Programming Language :: Python :: 3.8
Classifier: Programming Language :: Python :: 3.9
Classifier: Programming Language :: Python :: 3.10
Classifier: Programming Language :: Python :: 3.11
Classifier: Topic :: Office/Business :: Financial :: Investment
Classifier: Topic :: Software Development :: Libraries
Requires-Python: >=3.6
License-File: LICENSE
Requires-Dist: pandas (<1.4)
Provides-Extra: test
Requires-Dist: coverage[toml] (>=5.0.2) ; extra == 'test'
Requires-Dist: matplotlib ; extra == 'test'
Requires-Dist: pytest ; extra == 'test'
